Textcipher/Ciphers.py
Textcipher/__init__.py
Textcipher-0.0.1.dist-info/LICENSE.txt
Textcipher-0.0.1.dist-info/METADATA
Textcipher-0.0.1.dist-info/WHEEL
Textcipher-0.0.1.dist-info/top_level.txt
Textcipher-0.0.1.dist-info/RECORD
