Metadata-Version: 2.1
Name: Textcipher
Version: 0.0.1
Summary: A text encryption/decryption package
Home-page: https://github.com/Shetty073/Textcipher
Author: Ashish Shetty
Author-email: shetty073@gmail.com
License: UNKNOWN
Platform: UNKNOWN
Classifier: Programming Language :: Python :: 3
Classifier: License :: OSI Approved :: MIT License
Classifier: Operating System :: OS Independent
